{
  "width": 256,
  "height": 256,
  "background": "#ffffff",
  "palette": [
    "#204ddf",
    "#3a20df",
    "#8220df",
    "#ca20df",
    "#df20ad",
    "#df2065",
    "#df2220",
    "#df6a20",
    "#dfb220",
    "#c5df20",
    "#7ddf20",
    "#35df20",
    "#20df52",
    "#20df9a",
    "#20dddf",
    "#2095df"
  ],
  "shapes": [
    {
      "kind": "circle",
      "cx": 233,
      "cy": 231,
      "r": 19,
      "color": "#204ddf"
    },
    {
      "kind": "circle",
      "cx": 175,
      "cy": 112,
      "r": 21,
      "color": "#3a20df"
    },
    {
      "kind": "triangle",
      "p1": {
        "x": 34,
        "y": 96
      },
      "p2": {
        "x": 51,
        "y": 97
      },
      "p3": {
        "x": 42,
        "y": 115
      },
      "color": "#8220df"
    },
    {
      "kind": "circle",
      "cx": 188,
      "cy": 80,
      "r": 17,
      "color": "#ca20df"
    },
    {
      "kind": "circle",
      "cx": 111,
      "cy": 149,
      "r": 11,
      "color": "#df20ad"
    },
    {
      "kind": "triangle",
      "p1": {
        "x": 162,
        "y": 132
      },
      "p2": {
        "x": 174,
        "y": 133
      },
      "p3": {
        "x": 170,
        "y": 146
      },
      "color": "#df2065"
    },
    {
      "kind": "rectangle",
      "x": 55,
      "y": 174,
      "w": 24,
      "h": 27,
      "color": "#df2220"
    },
    {
      "kind": "circle",
      "cx": 108,
      "cy": 72,
      "r": 16,
      "color": "#df6a20"
    },
    {
      "kind": "circle",
      "cx": 144,
      "cy": 49,
      "r": 23,
      "color": "#dfb220"
    },
    {
      "kind": "circle",
      "cx": 157,
      "cy": 214,
      "r": 11,
      "color": "#c5df20"
    },
    {
      "kind": "circle",
      "cx": 172,
      "cy": 108,
      "r": 27,
      "color": "#7ddf20"
    },
    {
      "kind": "circle",
      "cx": 224,
      "cy": 218,
      "r": 22,
      "color": "#35df20"
    },
    {
      "kind": "triangle",
      "p1": {
        "x": 215,
        "y": 26
      },
      "p2": {
        "x": 241,
        "y": 37
      },
      "p3": {
        "x": 222,
        "y": 51
      },
      "color": "#20df52"
    },
    {
      "kind": "triangle",
      "p1": {
        "x": 171,
        "y": 38
      },
      "p2": {
        "x": 186,
        "y": 51
      },
      "p3": {
        "x": 169,
        "y": 64
      },
      "color": "#20df9a"
    },
    {
      "kind": "triangle",
      "p1": {
        "x": 29,
        "y": 96
      },
      "p2": {
        "x": 41,
        "y": 101
      },
      "p3": {
        "x": 35,
        "y": 113
      },
      "color": "#20dddf"
    },
    {
      "kind": "rectangle",
      "x": 209,
      "y": 63,
      "w": 12,
      "h": 24,
      "color": "#2095df"
    }
  ],
  "seed": 1
}